{
	"name": "KLN_jobstepping",
	"properties": {
		"type": "MappingDataFlow",
		"typeProperties": {
			"sources": [
				{
					"linkedService": {
						"referenceName": "linkedService1",
						"type": "LinkedServiceReference"
					},
					"name": "source1"
				},
				{
					"linkedService": {
						"referenceName": "linkedService1",
						"type": "LinkedServiceReference"
					},
					"name": "xpseceuser"
				}
			],
			"sinks": [
				{
					"linkedService": {
						"referenceName": "linkedService1",
						"type": "LinkedServiceReference"
					},
					"name": "sink1"
				}
			],
			"transformations": [
				{
					"name": "filter1"
				},
				{
					"name": "window1"
				},
				{
					"name": "derivedColumn1"
				},
				{
					"name": "AlterRow1"
				},
				{
					"name": "join1"
				},
				{
					"name": "select1"
				},
				{
					"name": "aggregate1"
				},
				{
					"name": "derivedColumn2"
				},
				{
					"name": "filter2"
				},
				{
					"name": "select2"
				}
			],
			"scriptLines": [
				"source(output(",
				"          ecEventGkey as long,",
				"          yardGkey as long,",
				"          YardID as string,",
				"          FcyID as string,",
				"          cheKind as string,",
				"          cheName as string,",
				"          cheID as long,",
				"          type as short,",
				"          subType as short,",
				"          typeDescription as string,",
				"          fromCheIdName as short,",
				"          ToCheIdName as short,",
				"          unitIdName as string,",
				"          powName as string,",
				"          poolName as string,",
				"          workQueue as string,",
				"          travelDistance as short,",
				"          moveKind as string,",
				"          isTwin as boolean,",
				"          startDistance as short,",
				"          unitReference as string,",
				"          tranId as string,",
				"          locType as string,",
				"          locId as string,",
				"          locSlot as string,",
				"          opsPosId as string,",
				"          unladenLoctype as string,",
				"          unladenLocId as string,",
				"          unladenLocSlot as string,",
				"          ladenLoctype as string,",
				"          ladenLocId as string,",
				"          laden_LocSlot as string,",
				"          operatorName as string,",
				"          EcEventTime as timestamp,",
				"          Year as integer,",
				"          Month as integer,",
				"          Week as integer",
				"     ),",
				"     allowSchemaDrift: true,",
				"     validateSchema: false,",
				"     ignoreNoFilesFound: false,",
				"     format: 'delta',",
				"     fileSystem: 'kln',",
				"     folderPath: 'silver/ecevents') ~> source1",
				"source(output(",
				"          GKEY as long,",
				"          USER_ID as string,",
				"          NAME as string,",
				"          YARD as integer",
				"     ),",
				"     useSchema: false,",
				"     allowSchemaDrift: true,",
				"     validateSchema: false,",
				"     ignoreNoFilesFound: false,",
				"     format: 'delimited',",
				"     fileSystem: 'kln',",
				"     folderPath: 'bronze/xpsecuser',",
				"     columnDelimiter: ',',",
				"     escapeChar: '\\\\',",
				"     quoteChar: '\\\"',",
				"     columnNamesAsHeader: true) ~> xpseceuser",
				"select2 filter(not(isNull(ecEventGkey)) && cheKind==\"ITV\" && (eventTypeDescription==\"AYCO\" || eventTypeDescription==\"TVDR\" || eventTypeDescription==\"AVDR\" || eventTypeDescription==\"AVCO\" || eventTypeDescription==\"TYDR\" || eventTypeDescription==\"AYDR\" ) && (moveKind==\"DSCH\"||moveKind==\"LOAD\")) ~> filter1",
				"filter1 window(over(cheID),",
				"     asc(EcEventTime, true),",
				"     asc(ecEventGkey, true),",
				"     startRowOffset: -1L,",
				"     endRowOffset: 1L,",
				"     eventTypeDescription_nxt = lead(eventTypeDescription),",
				"          eventTypeDescription_lag = lag(eventTypeDescription)) ~> window1",
				"window1 derive(jobStep = iif(eventTypeDescription == 'TVDR',\r",
				"    iif(eventTypeDescription_nxt == 'AVDR' && eventTypeDescription_lag == 'AYCO', 1, 0),\r",
				"    iif(eventTypeDescription == 'TYDR',\r",
				"        iif(eventTypeDescription_nxt == 'AYDR' && eventTypeDescription_lag == 'AVCO', 1, 0),\r",
				"        toInteger(null())\r",
				"    )\r",
				")\r",
				"\r",
				",",
				"          Types = case(\r",
				"    eventTypeDescription == 'TVDR', \r",
				"        iif((eventTypeDescription_nxt != 'AVDR' || isNull(eventTypeDescription_nxt)) && (eventTypeDescription_lag != 'AYCO' || isNull(eventTypeDescription_lag)), 'Violation at Vessel and Yard',\r",
				"        iif(eventTypeDescription_nxt != 'AVDR' || isNull(eventTypeDescription_nxt), 'Load-Miss Arrive at Ship',\r",
				"        iif(eventTypeDescription_lag != 'AYCO' || isNull(eventTypeDescription_lag), 'Load-Miss Arrive at Row', 'No Violation'))),\r",
				"    \r",
				"    eventTypeDescription == 'TYDR', \r",
				"        iif((eventTypeDescription_nxt != 'AYDR' || isNull(eventTypeDescription_nxt)) && (eventTypeDescription_lag != 'AVCO' || isNull(eventTypeDescription_lag)), 'Violation at Vessel and Yard',\r",
				"        iif(eventTypeDescription_nxt != 'AYDR' || isNull(eventTypeDescription_nxt), 'DSCH-Miss Arrive at Row',\r",
				"        iif(eventTypeDescription_lag != 'AVCO' || isNull(eventTypeDescription_lag), 'DSCH-Miss Arrive at Ship', 'No Violation'))),\r",
				"    \r",
				"    toString(null())\r",
				"),",
				"          operatorName = regexReplace(operatorName, `[^a-zA-Z0-9]`, '')) ~> derivedColumn1",
				"select1 alterRow(upsertIf(true()),",
				"     insertIf(true())) ~> AlterRow1",
				"derivedColumn1, filter2 join(operatorName == USER_ID,",
				"     joinType:'left',",
				"     matchType:'exact',",
				"     ignoreSpaces: false,",
				"     broadcast: 'auto')~> join1",
				"join1 select(mapColumn(",
				"          ecEventGkey,",
				"          yardGkey,",
				"          YardID,",
				"          FcyID,",
				"          cheKind,",
				"          CHE_Name = cheName,",
				"          eventType = type,",
				"          eventSubType = subType,",
				"          eventTypeDescription,",
				"          unit,",
				"          pow = powName,",
				"          pool = poolName,",
				"          travelDistance,",
				"          moveKind,",
				"          startDistance,",
				"          EcEventTime,",
				"          cheID,",
				"          Year,",
				"          Month,",
				"          Week,",
				"          OperatorID = operatorName,",
				"          eventTypeDescription_nxt,",
				"          unit_nxt,",
				"          cheID_nxt,",
				"          EcEventTime_nxt,",
				"          OperatorName = NAME,",
				"          jobStep",
				"     ),",
				"     skipDuplicateMapInputs: true,",
				"     skipDuplicateMapOutputs: true) ~> select1",
				"derivedColumn2 aggregate(groupBy(USER_ID),",
				"     NAME = last(NAME)) ~> aggregate1",
				"xpseceuser derive(USER_ID = regexReplace(USER_ID, `[^a-zA-Z0-9]`, ''),",
				"          NAME = regexReplace(NAME, `[^a-zA-Z0-9]`, ' ')) ~> derivedColumn2",
				"aggregate1 filter(not(isNull(USER_ID))) ~> filter2",
				"source1 select(mapColumn(",
				"          ecEventGkey,",
				"          yardGkey,",
				"          YardID,",
				"          FcyID,",
				"          cheKind,",
				"          cheName,",
				"          cheID,",
				"          type,",
				"          subType,",
				"          eventTypeDescription = typeDescription,",
				"          fromCheIdName,",
				"          ToCheIdName,",
				"          unit = unitIdName,",
				"          powName,",
				"          poolName,",
				"          workQueue,",
				"          travelDistance,",
				"          moveKind,",
				"          isTwin,",
				"          startDistance,",
				"          unitReference,",
				"          tranId,",
				"          locType,",
				"          locId,",
				"          locSlot,",
				"          opsPosId,",
				"          unladenLoctype,",
				"          unladenLocId,",
				"          unladenLocSlot,",
				"          ladenLoctype,",
				"          ladenLocId,",
				"          laden_LocSlot,",
				"          operatorName,",
				"          EcEventTime,",
				"          Year,",
				"          Month,",
				"          Week",
				"     ),",
				"     skipDuplicateMapInputs: true,",
				"     skipDuplicateMapOutputs: true) ~> select2",
				"AlterRow1 sink(allowSchemaDrift: true,",
				"     validateSchema: false,",
				"     format: 'delta',",
				"     fileSystem: 'kln',",
				"     folderPath: 'gold/jobstep',",
				"     mergeSchema: true,",
				"     autoCompact: true,",
				"     optimizedWrite: true,",
				"     vacuum: 0,",
				"     deletable: true,",
				"     insertable: false,",
				"     updateable: true,",
				"     upsertable: true,",
				"     keys:['ecEventGkey'],",
				"     umask: 0777,",
				"     preCommands: [],",
				"     postCommands: [],",
				"     skipDuplicateMapInputs: true,",
				"     skipDuplicateMapOutputs: true) ~> sink1"
			]
		}
	}
}